pba/__init__.py
pba/cbox.py
pba/copula.py
pba/core.py
pba/interval.py
pba/logical.py
pba/pbox.py
pba/pbox_constructors/__init__.py
pba/pbox_constructors/distributions.py
pba/pbox_constructors/non_parametric.py
pba/pbox_constructors/parametric.py
pba-0.90.4.dist-info/licenses/LICENSE
pba-0.90.4.dist-info/METADATA
pba-0.90.4.dist-info/WHEEL
pba-0.90.4.dist-info/top_level.txt
pba-0.90.4.dist-info/RECORD
