Metadata-Version: 2.4
Name: pba
Version: 0.90.4
Summary: Probability Bounds Analysis in Python
Home-page: https://github.com/Institute-for-Risk-and-Uncertainty/pba-for-python
Author: Nick Gray
Author-email: Nick Gray <ngg@liv.ac.uk>
License: MIT License
Project-URL: Documentation, https://pba-for-python.readthedocs.io/en/latest/
Project-URL: Repository, https://github.com/Institute-for-Risk-and-Uncertainty/pba-for-python
License-File: LICENSE
Requires-Dist: numpy>=1.26.2
Requires-Dist: scipy>=1.11.4
Requires-Dist: matplotlib>=3.8.2
Dynamic: author
Dynamic: home-page
Dynamic: license-file
